chembee_actions/__init__.py
chembee_actions/applicability.py
chembee_actions/benchmark_algorithms.py
chembee_actions/calibration.py
chembee_actions/classifier_fit.py
chembee_actions/clf_list.py
chembee_actions/cross_validation.py
chembee_actions/evaluation.py
chembee_actions/feature_extraction.py
chembee_actions/get_false_predictions.py
chembee_actions/get_undersampled_data.py
chembee_actions/save_model.py
chembee_actions/search.py
chembee_config/__init__.py
chembee_config/benchmark/BenchmarkAlgorithm.py
chembee_config/benchmark/__init__.py
chembee_config/benchmark/grid_search_cv.py
chembee_config/benchmark/kmeans.py
chembee_config/benchmark/knn.py
chembee_config/benchmark/linear_regression.py
chembee_config/benchmark/logistic_regression.py
chembee_config/benchmark/mlp_classifier.py
chembee_config/benchmark/naive_bayes.py
chembee_config/benchmark/random_forest.py
chembee_config/benchmark/restricted_bm.py
chembee_config/benchmark/spectral_clustering.py
chembee_config/benchmark/svc.py
chembee_config/benchmark/svc_poly.py
chembee_config/calibration/__init__.py
chembee_config/calibration/kmeans.py
chembee_config/calibration/knn.py
chembee_config/calibration/linear_regression.py
chembee_config/calibration/logistic_regression.py
chembee_config/calibration/mlp_classifier.py
chembee_config/calibration/naive_bayes.py
chembee_config/calibration/random_forest.py
chembee_config/calibration/restricted_bm.py
chembee_config/calibration/spectral_clustering.py
chembee_config/calibration/svc.py
chembee_config/calibration/svc_poly.py
chembee_datasets/BioDegDataSet.py
chembee_datasets/BreastCancer.py
chembee_datasets/ChemicalDataSet.py
chembee_datasets/DataSet.py
chembee_datasets/IrisDataSet.py
chembee_datasets/__init__.py
chembee_plotting/__init__.py
chembee_plotting/benchmarking.py
chembee_plotting/calibration.py
chembee_plotting/compounds.py
chembee_plotting/evaluation.py
chembee_plotting/feature_extraction.py
chembee_plotting/graphics.py
chembee_plotting/lipinski.py
chembee-0.0.4.36.dist-info/LICENSE
chembee-0.0.4.36.dist-info/METADATA
chembee-0.0.4.36.dist-info/WHEEL
chembee-0.0.4.36.dist-info/top_level.txt
chembee-0.0.4.36.dist-info/RECORD
