Metadata-Version: 2.1
Name: chembee
Version: 0.0.4.36
Summary: Package applying Machine Learning and AI to designing chemicals
Home-page: http://www.codeberg/cap_jmk/chembee
Author: Julian M. Kleber
Author-email: juilian.kleber@sail.black
Classifier: Programming Language :: Python :: 3
Classifier: License :: OSI Approved :: GNU Affero General Public License v3 or later (AGPLv3+)
Classifier: Operating System :: OS Independent
Requires-Python: >=3.9
License-File: LICENSE
